actagm/__init__.py
actagm/adapters.py
actagm/agm_helper.py
actagm/auth.py
actagm-0.1.1.dist-info/DESCRIPTION.rst
actagm-0.1.1.dist-info/METADATA
actagm-0.1.1.dist-info/RECORD
actagm-0.1.1.dist-info/WHEEL
actagm-0.1.1.dist-info/metadata.json
actagm-0.1.1.dist-info/top_level.txt
