Metadata-Version: 2.0
Name: actagm
Version: 0.1.1
Summary: A utility for agm.
Home-page: https://github.com/Brian-Williams/actagm
Author: Brian Williams
Author-email: briancmwilliams@gmail.com
License: UNKNOWN
Requires-Dist: requests
Provides-Extra: test
Requires-Dist: flake8; extra == 'test'
Requires-Dist: pytest (>=2.9.0); extra == 'test'
